{
  "_WARNING": "DO NOT put real credentials here. This file is tracked by git.",
  "_INSTRUCTIONS": "Set the GOOGLE_APPLICATION_CREDENTIALS env var to point to your real service account key file, or use workload identity federation in production.",
  "type": "service_account",
  "project_id": "REPLACE_WITH_YOUR_PROJECT_ID",
  "private_key_id": "REPLACE_ME",
  "private_key": "REPLACE_ME — rotate the old key immediately at https://console.cloud.google.com/iam-admin/serviceaccounts",
  "client_email": "REPLACE_ME@YOUR_PROJECT.iam.gserviceaccount.com",
  "client_id": "REPLACE_ME",
  "auth_uri": "https://accounts.google.com/o/oauth2/auth",
  "token_uri": "https://oauth2.googleapis.com/token",
  "auth_provider_x509_cert_url": "https://www.googleapis.com/oauth2/v1/certs",
  "client_x509_cert_url": "REPLACE_ME",
  "universe_domain": "googleapis.com"
}